verylargebits/__init__.py
verylargebits/client.py
verylargebits-0.1.8.dist-info/DESCRIPTION.rst
verylargebits-0.1.8.dist-info/METADATA
verylargebits-0.1.8.dist-info/RECORD
verylargebits-0.1.8.dist-info/WHEEL
verylargebits-0.1.8.dist-info/metadata.json
verylargebits-0.1.8.dist-info/top_level.txt
